structsock.py
structsock-1.2.0.dist-info/LICENSE
structsock-1.2.0.dist-info/METADATA
structsock-1.2.0.dist-info/WHEEL
structsock-1.2.0.dist-info/top_level.txt
structsock-1.2.0.dist-info/RECORD
