Metadata-Version: 2.1
Name: structsock
Version: 1.2.0
Summary: A simple module to encapsulate the built-in socket with struct.pack.
Home-page: https://github.com/origamizyt/StructuredSocket
Author: origamizyt
Author-email: zhaoyitong18@163.com
License: UNKNOWN
Platform: UNKNOWN
Classifier: Programming Language :: Python :: 3
Classifier: License :: OSI Approved :: The Unlicense (Unlicense)
Classifier: Operating System :: OS Independent
Requires-Python: >=3
